{
  "nfl": [
    {
      "id": 1,
      "stadium_name": "State Farm Stadium",
      "team_name": "Arizona Cardinals",
      "city": "Glendale",
      "state": "AZ",
      "image": "https://en.wikipedia.org/wiki/List_of_current_National_Football_League_stadiums#/media/File:University_of_Phoenix_Stadium_no_field.jpg"
    },
    {
      "id": 2,
      "stadium_name": "Mercedes-Benz Stadium",
      "team_name": "Atlanta Falcons",
      "city": "Atlanta",
      "state": "GA",
      "image": "https://en.wikipedia.org/wiki/List_of_current_National_Football_League_stadiums#/media/File:Peach_Bowl_Pre-game_(39431667481).jpg"
    },
    {
      "id": 3,
      "stadium_name": "M&T Bank Stadium",
      "team_name": "Baltimore Ravens",
      "city": "Baltimore",
      "state": "MD",
      "image": "https://en.wikipedia.org/wiki/List_of_current_National_Football_League_stadiums#/media/File:M&T_Bank_Stadium_DoD.jpg"
    },
    {
      "id": 4,
      "stadium_name": "Highmark Stadium",
      "team_name": "Buffalo Bills",
      "city": "Orchard Park",
      "state": "NY",
      "image": "https://en.wikipedia.org/wiki/List_of_current_National_Football_League_stadiums#/media/File:Bills.jpg"
    },
    {
      "id": 5,
      "stadium_name": "Bank of America Stadium",
      "team_name": "Carolina Panthers",
      "city": "Charlotte",
      "state": "NC",
      "image": "http://www.pngmart.com/files/3/Toy-Story-Woody-PNG-Photos.png"
    },
    {
      "id": 6,
      "stadium_name": "Soldier Field",
      "team_name": "Chicago Bears",
      "city": "Chicago",
      "state": "IL",
      "image": "http://www.pngmart.com/files/3/Toy-Story-Woody-PNG-Photos.png"
    },
    {
      "id": 7,
      "stadium_name": "Paul Brown Stadium",
      "team_name": "Cincinnati Bengals",
      "city": "Cincinnati",
      "state": "OH",
      "image": "http://www.pngmart.com/files/3/Toy-Story-Woody-PNG-Photos.png"
    },
    {
      "id": 8,
      "stadium_name": "FirstEnergy Stadium",
      "team_name": "Cleveland Browns",
      "city": "Cleveland",
      "state": "OH",
      "image": "http://www.pngmart.com/files/3/Toy-Story-Woody-PNG-Photos.png"
    },
    {
      "id": 9,
      "stadium_name": "AT&T Stadium",
      "team_name": "Dallas Cowboys",
      "city": "Arlington",
      "state": "TX",
      "image": "http://www.pngmart.com/files/3/Toy-Story-Woody-PNG-Photos.png"
    },
    {
      "id": 10,
      "stadium_name": "Empower Field at Mile High",
      "team_name": "Denver Broncos",
      "city": "Denver",
      "state": "CO",
      "image": "http://www.pngmart.com/files/3/Toy-Story-Woody-PNG-Photos.png"
    },
    {
      "id": 11,
      "stadium_name": "Ford Field",
      "team_name": "Detroit Lions",
      "city": "Detroit",
      "state": "MI",
      "image": "http://www.pngmart.com/files/3/Toy-Story-Woody-PNG-Photos.png"
    },
    {
      "id": 12,
      "stadium_name": "Lambeau Field",
      "team_name": "Green Bay Packers",
      "city": "Green Bay",
      "state": "WI",
      "image": "http://www.pngmart.com/files/3/Toy-Story-Woody-PNG-Photos.png"
    },
    {
      "id": 13,
      "stadium_name": "NRG Stadium",
      "team_name": "Houston Texans",
      "city": "Houston",
      "state": "TX",
      "image": "http://www.pngmart.com/files/3/Toy-Story-Woody-PNG-Photos.png"
    },
    {
      "id": 14,
      "stadium_name": "Lucas Oil Stadium",
      "team_name": "Indianapolis Colts",
      "city": "Indianapolis",
      "state": "IN",
      "image": "http://www.pngmart.com/files/3/Toy-Story-Woody-PNG-Photos.png"
    },
    {
      "id": 15,
      "stadium_name": "TIAA Bank Field",
      "team_name": "Jacksonville Jaguars",
      "city": "Jacksonville",
      "state": "FL",
      "image": "http://www.pngmart.com/files/3/Toy-Story-Woody-PNG-Photos.png"
    },
    {
      "id": 16,
      "stadium_name": "Geha Field at Arrowhead Stadium",
      "team_name": "Kansas City Chiefs",
      "city": "Kansas City",
      "state": "MO",
      "image": "http://www.pngmart.com/files/3/Toy-Story-Woody-PNG-Photos.png"
    },
    {
      "id": 17,
      "stadium_name": "Allegiant Stadium",
      "team_name": "Las Vegas Raiders",
      "city": "Paradise",
      "state": "NV",
      "image": "http://www.pngmart.com/files/3/Toy-Story-Woody-PNG-Photos.png"
    },
    {
      "id": 18,
      "stadium_name": "SoFi Stadium",
      "team_name": "Los Angeles Chargers",
      "city": "Inglewood",
      "state": "CA",
      "image": "http://www.pngmart.com/files/3/Toy-Story-Woody-PNG-Photos.png"
    },
    {
      "id": 19,
      "stadium_name": "SoFi Stadium",
      "team_name": "Los Angeles Rams",
      "city": "Inglewood",
      "state": "CA",
      "image": "http://www.pngmart.com/files/3/Toy-Story-Woody-PNG-Photos.png"
    },
    {
      "id": 20,
      "stadium_name": "Hard Rock Stadium",
      "team_name": "Miami Dolphins",
      "city": "Miami Gardens",
      "state": "FL",
      "image": "http://www.pngmart.com/files/3/Toy-Story-Woody-PNG-Photos.png"
    },
    {
      "id": 21,
      "stadium_name": "U.S. Bank Stadium",
      "team_name": "Minnesota Vikings",
      "city": "Minneapolis",
      "state": "MN",
      "image": "http://www.pngmart.com/files/3/Toy-Story-Woody-PNG-Photos.png"
    },
    {
      "id": 22,
      "stadium_name": "Gillette Stadium",
      "team_name": "New England Patriots",
      "city": "Foxborough",
      "state": "MA",
      "image": "http://www.pngmart.com/files/3/Toy-Story-Woody-PNG-Photos.png"
    },
    {
      "id": 23,
      "stadium_name": "Caesars Superdome",
      "team_name": "New Orleans Saints",
      "city": "New Orleans",
      "state": "LA",
      "image": "http://www.pngmart.com/files/3/Toy-Story-Woody-PNG-Photos.png"
    },
    {
      "id": 24,
      "stadium_name": "MetLife Stadium",
      "team_name": "New York Giants",
      "city": "East Rutherford",
      "state": "NJ",
      "image": "http://www.pngmart.com/files/3/Toy-Story-Woody-PNG-Photos.png"
    },
    {
      "id": 25,
      "stadium_name": "MetLife Stadium",
      "team_name": "New York Jets",
      "city": "East Rutherford",
      "state": "NJ",
      "image": "http://www.pngmart.com/files/3/Toy-Story-Woody-PNG-Photos.png"
    },
    {
      "id": 26,
      "stadium_name": "Lincoln Financial Field",
      "team_name": "Philadelphia Eagles",
      "city": "Philadelphia",
      "state": "PA",
      "image": "http://www.pngmart.com/files/3/Toy-Story-Woody-PNG-Photos.png"
    },
    {
      "id": 27,
      "stadium_name": "Heinz Field",
      "team_name": "Pittsburgh Steelers",
      "city": "Pittsburgh",
      "state": "PA",
      "image": "http://www.pngmart.com/files/3/Toy-Story-Woody-PNG-Photos.png"
    },
    {
      "id": 28,
      "stadium_name": "Levi's Stadium",
      "team_name": "San Francisco 49ers",
      "city": "Santa Clara",
      "state": "CA",
      "image": "http://www.pngmart.com/files/3/Toy-Story-Woody-PNG-Photos.png"
    },
    {
      "id": 29,
      "stadium_name": "Lumen Field",
      "team_name": "Seattle Seahawks",
      "city": "Seattle",
      "state": "WA",
      "image": "http://www.pngmart.com/files/3/Toy-Story-Woody-PNG-Photos.png"
    },
    {
      "id": 30,
      "stadium_name": "Raymond James Stadium",
      "team_name": "Tampa Bay Buccaneers",
      "city": "Tampa",
      "state": "FL",
      "image": "http://www.pngmart.com/files/3/Toy-Story-Woody-PNG-Photos.png"
    },
    {
      "id": 31,
      "stadium_name": "Nissan Stadium",
      "team_name": "Tennessee Titans",
      "city": "Nashville",
      "state": "TN",
      "image": "http://www.pngmart.com/files/3/Toy-Story-Woody-PNG-Photos.png"
    },
    {
      "id": 32,
      "stadium_name": "FedEx Field",
      "team_name": "Washington Football Team",
      "city": "Landover",
      "state": "MD",
      "image": "http://www.pngmart.com/files/3/Toy-Story-Woody-PNG-Photos.png"
    }
  ]
}